{
  "appKey": "",
  "appSecret": "",
  "encryptJs": true,
  "excludeScenes": [
    "ce90c548-a936-485d-90e8-767286cb1fea",
    "408e5c63-4c22-4560-b94f-d0641712455e"
  ],
  "fb-instant-games": {},
  "includeAnySDK": false,
  "includeSDKBox": false,
  "inlineSpriteFrames": true,
  "inlineSpriteFrames_native": false,
  "jailbreakPlatform": false,
  "md5Cache": true,
  "mergeStartScene": false,
  "oauthLoginServer": "",
  "optimizeHotUpdate": false,
  "orientation": {
    "landscapeLeft": true,
    "landscapeRight": true,
    "portrait": false,
    "upsideDown": false
  },
  "packageName": "org.cocos2d.HeroesOfSteel",
  "privateKey": "",
  "qqplay": {
    "REMOTE_SERVER_ROOT": "",
    "orientation": "portrait"
  },
  "renderMode": "0",
  "startScene": "049cefe1-35c0-4886-9815-b235c3f8164f",
  "title": "HeroesOfSteel",
  "webOrientation": "landscape",
  "wechatgame": {
    "REMOTE_SERVER_ROOT": "",
    "appid": "wx6ac3f5090a6b99c5",
    "isSubdomain": false,
    "orientation": "portrait",
    "subContext": ""
  },
  "xxteaKey": "da65b703-a139-47",
  "zipCompressJs": true
}